odtlearn/__init__.py
odtlearn/_version.py
odtlearn/constants.py
odtlearn/datasets.py
odtlearn/fair_oct.py
odtlearn/flow_oct.py
odtlearn/flow_oct_ms.py
odtlearn/flow_oct_ss.py
odtlearn/flow_opt.py
odtlearn/flow_opt_ms.py
odtlearn/flow_opt_ss.py
odtlearn/opt_ct.py
odtlearn/opt_dt.py
odtlearn/opt_pt.py
odtlearn/robust_oct.py
odtlearn/data/balance-scale_enc.csv
odtlearn/data/example_1.npz
odtlearn/data/example_1_robust.npz
odtlearn/data/example_2.npz
odtlearn/data/fairness_example.npz
odtlearn/data/monk2.csv
odtlearn/data/prescriptive/test_v2_200.csv
odtlearn/data/prescriptive/train_50.csv
odtlearn/data/prescriptive/train_v2_100.csv
odtlearn/tests/__init__.py
odtlearn/tests/conftest.py
odtlearn/tests/test_FairOCT.py
odtlearn/tests/test_FlowOPT.py
odtlearn/tests/test_Flow_Benders_OCT.py
odtlearn/tests/test_RobustOCT.py
odtlearn/tests/test_abstract.py
odtlearn/tests/test_datasets.py
odtlearn/tests/test_solvers.py
odtlearn/tests/test_tree.py
odtlearn/tests/test_utils.py
odtlearn/tests/test_validation.py
odtlearn/utils/Tree.py
odtlearn/utils/TreePlotter.py
odtlearn/utils/__init__.py
odtlearn/utils/_reingold_tilford.py
odtlearn/utils/binarize.py
odtlearn/utils/callback_helpers.py
odtlearn/utils/callbacks.py
odtlearn/utils/cbc_solver.py
odtlearn/utils/gb_solver.py
odtlearn/utils/mip_cbc.py
odtlearn/utils/scip_solver.py
odtlearn/utils/solver.py
odtlearn/utils/validation.py
odtlearn-1.0.0.dist-info/LICENSE
odtlearn-1.0.0.dist-info/METADATA
odtlearn-1.0.0.dist-info/WHEEL
odtlearn-1.0.0.dist-info/top_level.txt
odtlearn-1.0.0.dist-info/RECORD
